{
  "Films": [
    {
      "id": "gPq0iG7vaqQ",
      "title": "Amnesia"
    },
    {
      "id": "IZ9AG4UqrM0",
      "title": "Pekee Yangu"
    },
    {
      "id": "SONljLNmyXk",
      "title": "The Untouched"
    },
    {
      "id": "E0xu2BPETqA",
      "title": "Bad is Bad"
    }
  ],
  "Shows": [
    {
      "id": "P3uGSj5Am6Q",
      "title": "Inkwire"
    },
    {
      "id": "6bD7h6sIpxs",
      "title": "Alma Ras One mic"
    },
    {
      "id": "JDXbRvx2Cv0",
      "title": "Kuky One mic"
    },
  
    {
      "id": "WP1NZBzXRjs",
      "title": "Blackbird One mic"
    }

  ],
  "Music Videos": [
    {
      "id": "2TjOPCPL2J0",
      "title": "Blame You"
    },
    {
      "id": "zW7WcXJKWBo",
      "title": "Westside"
    },
    {
      "id": "4ssZtqFppcs",
      "title": "Oya Oya"
    },
    {
      "id": "o_H5pCyxqnA",
      "title": "Shut it down"
    },
    {
      "id": "r4hbRySVpnM",
      "title": "Final Warning"
    },

    {
      "id": "sabJr9kyWZw",
      "title": "IA Freestyle"
    },
    {
      "id": "RCMzpSePlrI",
      "title": "Im Good"
    },
    {
      "id": "umRi31Uc6Ag",
      "title": "Legend"
    }
  ]
}
